LICENSE
MANIFEST.in
README.rst
changelog
requirements.txt
setup.py
rfc_xmldiff.egg-info/PKG-INFO
rfc_xmldiff.egg-info/SOURCES.txt
rfc_xmldiff.egg-info/dependency_links.txt
rfc_xmldiff.egg-info/entry_points.txt
rfc_xmldiff.egg-info/not-zip-safe
rfc_xmldiff.egg-info/requires.txt
rfc_xmldiff.egg-info/top_level.txt
test/test.py
xmldiff/DiffNode.py
xmldiff/EditDistance.py
xmldiff/EditItem.py
xmldiff/__init__.py
xmldiff/run.py
xmldiff/zzs.c
xmldiff/zzs.py
xmldiff/zzs2.py
xmldiff/zzs_build.py
xmldiff/Templates/base.html
xmldiff/Templates/resize.js
xmldiff/Templates/single.html
xmldiff/Templates/wdiff.html