Metadata-Version: 1.2
Name: rfc-xmldiff
Version: 0.5.15
Summary: Create an HTML difference display from two XML input files.
Home-page: https://tools.ietf.org/tools/ietfdb/browser/brance/elft/xmldiff/
Author: Jim Schaad
Author-email: ietf@augustcellars.com
License: Simplified BSD
Keywords: compare xml RFC
Platform: UNKNOWN
Classifier: Development Status :: 2 - Pre-Alpha
Classifier: Intended Audience :: Other Audience
Classifier: Topic :: Text Processing
Classifier: Topic :: Text Processing :: Markup :: XML
Classifier: License :: OSI Approved :: BSD License
Classifier: Programming Language :: Python :: 2.7
Classifier: Programming Language :: Python :: 3.6
Requires-Python: >=2.7, !=3.0.*, !=3.1.*, !=3.2.*, <4
